{
  "id": "dbe78e14-4f1d-4b57-bb57-686af6e606a9",
  "prevId": "00000000-0000-0000-0000-000000000000",
  "version": "7",
  "dialect": "postgresql",
  "tables": {
    "public.users": {
      "name": "users",
      "schema": "",
      "columns": {
        "id": {
          "name": "id",
          "type": "integer",
          "primaryKey": true,
          "notNull": true,
          "identity": {
            "type": "always",
            "name": "users_id_seq",
            "schema": "public",
            "increment": "1",
            "startWith": "1",
            "minValue": "1",
            "maxValue": "2147483647",
            "cache": "1",
            "cycle": false
          }
        },
        "pronouns": {
          "name": "pronouns",
          "type": "text",
          "primaryKey": false,
          "notNull": false
        },
        "description": {
          "name": "description",
          "type": "text",
          "primaryKey": false,
          "notNull": false
        },
        "track": {
          "name": "track",
          "type": "text",
          "primaryKey": false,
          "notNull": false
        },
        "facebook": {
          "name": "facebook",
          "type": "text",
          "primaryKey": false,
          "notNull": false
        },
        "instagram": {
          "name": "instagram",
          "type": "text",
          "primaryKey": false,
          "notNull": false
        },
        "tiktok": {
          "name": "tiktok",
          "type": "text",
          "primaryKey": false,
          "notNull": false
        },
        "color_one": {
          "name": "color_one",
          "type": "text",
          "primaryKey": false,
          "notNull": false
        },
        "color_two": {
          "name": "color_two",
          "type": "text",
          "primaryKey": false,
          "notNull": false
        },
        "color_three": {
          "name": "color_three",
          "type": "text",
          "primaryKey": false,
          "notNull": false
        }
      },
      "indexes": {},
      "foreignKeys": {},
      "compositePrimaryKeys": {},
      "uniqueConstraints": {},
      "policies": {},
      "checkConstraints": {},
      "isRLSEnabled": false
    }
  },
  "enums": {},
  "schemas": {},
  "sequences": {},
  "roles": {},
  "policies": {},
  "views": {},
  "_meta": {
    "columns": {},
    "schemas": {},
    "tables": {}
  }
}